{
    "slug": "addthis",
    "name": "AddThis",
    "url": "addthis.com",
    "icon_url": "//datafox-favicons.s3.amazonaws.com/favicons/5130efc18989846a3600004e.ico",
    "logo_url": "//datafox-data.s3-us-west-1.amazonaws.com/images/cb_fc89cfdea28ee12c443cedccb6c93fd4.png",
    "founded_year": 2004,
    "location": "McLean, VA",
    "status": "Acquired",
    "stage": "Acquired",
    "top_keywords": [
        "advertising",
        "file sharing",
        "mobile social",
        "social media",
        "analytics"
    ],
    "number_of_employees": 137,
    "short_description": "AddThis provides social engagement tools, APIs and services personalizing\nwebsites for engagement, monetization and traffic boosting.",
    "long_description": "AddThis provides social engagement tools, APIs and services personalizing\nwebsites for engagement, monetization and traffic boosting.",
    "investors": [
        "SharesPost",
        "Institutional Venture Partners",
        "Revolution LLC",
        "QED Investors",
        "New Enterprise Associates",
        "Novak Biddle Venture Partners",
        "New Enterprise Associates",
        "Novak Biddle Venture Partners",
        "QED Investors",
        "SV Angel",
        "Amidzad Partners",
        "Signatures Capital LLC",
        "ZG Ventures",
        "Novak Biddle Venture Partners",
        "Revolution LLC",
        "ZG Ventures",
        "Novak Biddle Venture Partners"
    ]
}