{"id":"5291d3a577bc1f2070069c80","slug":"hackpad","name":"HackPad","overall_score":877,"object_type":"company","icon_url":"//datafox-favicons.s3.amazonaws.com/favicons/5291d3a577bc1f2070069c80.ico","url":"hackpad.com","founded_year":2011,"logo_url":"//datafox-data.s3-us-west-1.amazonaws.com/images/cb_a874e35ed14b81510701534e36415691.png","stage":"Acquired","status":"Acquired","location":null,"top_keywords":["productivity software","business productivity","document management","real time"],"pe_ratio":null,"market_cap":null,"revenue_estimate":null,"number_of_employees":null,"total_funding":0,"last_funding_date":"2012-03-01T08:00:00.000Z","twitter_handle":"hackpad","linkedin_id":null,"twitter_followers_count":2374,"angellist_followers_count":61,"short_description":"Smart collaborative documents. Company wiki. Personal notes. Event planning.\nClassroom collaboration.","long_description":"Smart collaborative documents. Company wiki. Personal notes. Event planning.\nClassroom collaboration."}