{"id":"546f48c5b921f79a7800035f","slug":"let’s-encrypt","name":"Let’s Encrypt","overall_score":417,"object_type":"company","icon_url":"//datafox-data.s3.amazonaws.com/favicons/546f48c5b921f79a7800035f.ico","url":"letsencrypt.org/","founded_year":null,"logo_url":"//datafox-data.s3-us-west-1.amazonaws.com/images/cb_c7da267c29a8f79752cc1fecd2e7a128.png","stage":null,"status":null,"location":null,"top_keywords":["internet"],"pe_ratio":null,"market_cap":null,"revenue_estimate":null,"number_of_employees":null,"total_funding":0,"last_funding_date":null,"twitter_handle":"letsencrypt","linkedin_id":null,"twitter_followers_count":44474,"angellist_followers_count":null,"short_description":"Let’s Encrypt is a free, automated, and open certificate authority (CA), run for\nthe public’s benefit.","long_description":"Let’s Encrypt is a free, automated, and open certificate authority (CA), run for\nthe public’s benefit. Let’s Encrypt is a service provided by the Internet\nSecurity Research Group (ISRG)."}